Waqar/tasks/4b_adder/4b_adder.sv
module adder_4b(input logic unsigned [3:0] a,b,
                output logic unsigned [4:0] c);


    assign c = a+b;

endmodule

Waqar/tasks/4b_adder/4b_adder_tb.sv
module adder_4b_tb();

    reg unsigned [3:0] a,b;
    wire unsigned [4:0] c;
    integer correct_check = 0; 
    integer incorrect_check = 0; 
    integer total_checks = 0;
     

    adder_4b dut (.a(a),
                  .b(b),
                  .c(c));
    
    integer i,j;
    logic [4:0] c_expected;

    initial begin
        for(i=0; i<16; i++) begin
            for(j=0; j<16; j++) begin
                a = i;
                b = j;
                c_expected = a+b;
                #10;
                if(c==c_expected)begin
                    $display("Check %d-> Passed %d: a = %d b = %d c = %d c_expected = %d", total_checks,correct_check,a,b,c,c_expected);
                    correct_check++;
                end
                else begin
                    $display("Check %d-> Failed %d: a = %d b = %d c = %d c_expected = %d", total_checks,incorrect_check,a,b,c,c_expected);
                    incorrect_check++;
                end 
                total_checks++;
            end
        end
        $display("Total checks = %d Correct = %d Incorrect = %d", total_checks,correct_check,incorrect_check);  
        $finish;     
    end


    initial begin
        $dumpfile("adder_4b.vcd");
        $dumpvars(0,adder_4b_tb);
    end

endmodule

Waqar/tasks/4b_adder/adder_4b.vcd
$date
	Thu Jul  4 12:00:48 2024
$end
$version
	ModelSim Version 2020.1
$end
$timescale
	1ps
$end

$scope module adder_4b_tb $end
$var reg 4 ! a [3:0] $end
$var reg 4 " b [3:0] $end
$var wire 1 # c [4] $end
$var wire 1 $ c [3] $end
$var wire 1 % c [2] $end
$var wire 1 & c [1] $end
$var wire 1 ' c [0] $end
$var integer 32 ( correct_check $end
$var integer 32 ) incorrect_check $end
$var integer 32 * total_checks $end
$var integer 32 + i $end
$var integer 32 , j $end
$var reg 5 - c_expected [4:0] $end

$scope module dut $end
$var wire 1 . a [3] $end
$var wire 1 / a [2] $end
$var wire 1 0 a [1] $end
$var wire 1 1 a [0] $end
$var wire 1 2 b [3] $end
$var wire 1 3 b [2] $end
$var wire 1 4 b [1] $end
$var wire 1 5 b [0] $end
$var reg 5 6 c [4:0] $end
$upscope $end
$upscope $end
$enddefinitions $end
#0
$dumpvars
b0 !
b0 "
b0 6
b0 -
b0 (
b0 )
b0 *
b0 +
b0 ,
0'
0&
0%
0$
0#
01
00
0/
0.
05
04
03
02
$end
#10
b1 (
b1 *
b1 ,
b1 "
b1 -
15
b1 6
1'
#20
b10 (
b10 *
b10 ,
b10 "
b10 -
05
14
b10 6
0'
1&
#30
b11 (
b11 *
b11 ,
b11 "
b11 -
15
b11 6
1'
#40
b100 (
b100 *
b100 ,
b100 "
b100 -
05
04
13
b100 6
0'
0&
1%
#50
b101 (
b101 *
b101 ,
b101 "
b101 -
15
b101 6
1'
#60
b110 (
b110 *
b110 ,
b110 "
b110 -
05
14
b110 6
0'
1&
#70
b111 (
b111 *
b111 ,
b111 "
b111 -
15
b111 6
1'
#80
b1000 (
b1000 *
b1000 ,
b1000 "
b1000 -
05
04
03
12
b1000 6
0'
0&
0%
1$
#90
b1001 (
b1001 *
b1001 ,
b1001 "
b1001 -
15
b1001 6
1'
#100
b1010 (
b1010 *
b1010 ,
b1010 "
b1010 -
05
14
b1010 6
0'
1&
#110
b1011 (
b1011 *
b1011 ,
b1011 "
b1011 -
15
b1011 6
1'
#120
b1100 (
b1100 *
b1100 ,
b1100 "
b1100 -
05
04
13
b1100 6
0'
0&
1%
#130
b1101 (
b1101 *
b1101 ,
b1101 "
b1101 -
15
b1101 6
1'
#140
b1110 (
b1110 *
b1110 ,
b1110 "
b1110 -
05
14
b1110 6
0'
1&
#150
b1111 (
b1111 *
b1111 ,
b1111 "
b1111 -
15
b1111 6
1'
#160
b10000 (
b10000 *
b10000 ,
b1 +
b0 ,
b1 !
b0 "
b1 -
05
04
03
02
11
b1 6
0&
0%
0$
#170
b10001 (
b10001 *
b1 ,
b1 "
b10 -
15
b10 6
0'
1&
#180
b10010 (
b10010 *
b10 ,
b10 "
b11 -
05
14
b11 6
1'
#190
b10011 (
b10011 *
b11 ,
b11 "
b100 -
15
b100 6
0'
0&
1%
#200
b10100 (
b10100 *
b100 ,
b100 "
b101 -
05
04
13
b101 6
1'
#210
b10101 (
b10101 *
b101 ,
b101 "
b110 -
15
b110 6
0'
1&
#220
b10110 (
b10110 *
b110 ,
b110 "
b111 -
05
14
b111 6
1'
#230
b10111 (
b10111 *
b111 ,
b111 "
b1000 -
15
b1000 6
0'
0&
0%
1$
#240
b11000 (
b11000 *
b1000 ,
b1000 "
b1001 -
05
04
03
12
b1001 6
1'
#250
b11001 (
b11001 *
b1001 ,
b1001 "
b1010 -
15
b1010 6
0'
1&
#260
b11010 (
b11010 *
b1010 ,
b1010 "
b1011 -
05
14
b1011 6
1'
#270
b11011 (
b11011 *
b1011 ,
b1011 "
b1100 -
15
b1100 6
0'
0&
1%
#280
b11100 (
b11100 *
b1100 ,
b1100 "
b1101 -
05
04
13
b1101 6
1'
#290
b11101 (
b11101 *
b1101 ,
b1101 "
b1110 -
15
b1110 6
0'
1&
#300
b11110 (
b11110 *
b1110 ,
b1110 "
b1111 -
05
14
b1111 6
1'
#310
b11111 (
b11111 *
b1111 ,
b1111 "
b10000 -
15
b10000 6
0'
0&
0%
0$
1#
#320
b100000 (
b100000 *
b10000 ,
b10 +
b0 ,
b10 !
b0 "
b10 -
05
04
03
02
01
10
b10 6
1&
0#
#330
b100001 (
b100001 *
b1 ,
b1 "
b11 -
15
b11 6
1'
#340
b100010 (
b100010 *
b10 ,
b10 "
b100 -
05
14
b100 6
0'
0&
1%
#350
b100011 (
b100011 *
b11 ,
b11 "
b101 -
15
b101 6
1'
#360
b100100 (
b100100 *
b100 ,
b100 "
b110 -
05
04
13
b110 6
0'
1&
#370
b100101 (
b100101 *
b101 ,
b101 "
b111 -
15
b111 6
1'
#380
b100110 (
b100110 *
b110 ,
b110 "
b1000 -
05
14
b1000 6
0'
0&
0%
1$
#390
b100111 (
b100111 *
b111 ,
b111 "
b1001 -
15
b1001 6
1'
#400
b101000 (
b101000 *
b1000 ,
b1000 "
b1010 -
05
04
03
12
b1010 6
0'
1&
#410
b101001 (
b101001 *
b1001 ,
b1001 "
b1011 -
15
b1011 6
1'
#420
b101010 (
b101010 *
b1010 ,
b1010 "
b1100 -
05
14
b1100 6
0'
0&
1%
#430
b101011 (
b101011 *
b1011 ,
b1011 "
b1101 -
15
b1101 6
1'
#440
b101100 (
b101100 *
b1100 ,
b1100 "
b1110 -
05
04
13
b1110 6
0'
1&
#450
b101101 (
b101101 *
b1101 ,
b1101 "
b1111 -
15
b1111 6
1'
#460
b101110 (
b101110 *
b1110 ,
b1110 "
b10000 -
05
14
b10000 6
0'
0&
0%
0$
1#
#470
b101111 (
b101111 *
b1111 ,
b1111 "
b10001 -
15
b10001 6
1'
#480
b110000 (
b110000 *
b10000 ,
b11 +
b0 ,
b11 !
b0 "
b11 -
05
04
03
02
11
b11 6
1&
0#
#490
b110001 (
b110001 *
b1 ,
b1 "
b100 -
15
b100 6
0'
0&
1%
#500
b110010 (
b110010 *
b10 ,
b10 "
b101 -
05
14
b101 6
1'
#510
b110011 (
b110011 *
b11 ,
b11 "
b110 -
15
b110 6
0'
1&
#520
b110100 (
b110100 *
b100 ,
b100 "
b111 -
05
04
13
b111 6
1'
#530
b110101 (
b110101 *
b101 ,
b101 "
b1000 -
15
b1000 6
0'
0&
0%
1$
#540
b110110 (
b110110 *
b110 ,
b110 "
b1001 -
05
14
b1001 6
1'
#550
b110111 (
b110111 *
b111 ,
b111 "
b1010 -
15
b1010 6
0'
1&
#560
b111000 (
b111000 *
b1000 ,
b1000 "
b1011 -
05
04
03
12
b1011 6
1'
#570
b111001 (
b111001 *
b1001 ,
b1001 "
b1100 -
15
b1100 6
0'
0&
1%
#580
b111010 (
b111010 *
b1010 ,
b1010 "
b1101 -
05
14
b1101 6
1'
#590
b111011 (
b111011 *
b1011 ,
b1011 "
b1110 -
15
b1110 6
0'
1&
#600
b111100 (
b111100 *
b1100 ,
b1100 "
b1111 -
05
04
13
b1111 6
1'
#610
b111101 (
b111101 *
b1101 ,
b1101 "
b10000 -
15
b10000 6
0'
0&
0%
0$
1#
#620
b111110 (
b111110 *
b1110 ,
b1110 "
b10001 -
05
14
b10001 6
1'
#630
b111111 (
b111111 *
b1111 ,
b1111 "
b10010 -
15
b10010 6
0'
1&
#640
b1000000 (
b1000000 *
b10000 ,
b100 +
b0 ,
b100 !
b0 "
b100 -
05
04
03
02
01
00
1/
b100 6
0&
1%
0#
#650
b1000001 (
b1000001 *
b1 ,
b1 "
b101 -
15
b101 6
1'
#660
b1000010 (
b1000010 *
b10 ,
b10 "
b110 -
05
14
b110 6
0'
1&
#670
b1000011 (
b1000011 *
b11 ,
b11 "
b111 -
15
b111 6
1'
#680
b1000100 (
b1000100 *
b100 ,
b100 "
b1000 -
05
04
13
b1000 6
0'
0&
0%
1$
#690
b1000101 (
b1000101 *
b101 ,
b101 "
b1001 -
15
b1001 6
1'
#700
b1000110 (
b1000110 *
b110 ,
b110 "
b1010 -
05
14
b1010 6
0'
1&
#710
b1000111 (
b1000111 *
b111 ,
b111 "
b1011 -
15
b1011 6
1'
#720
b1001000 (
b1001000 *
b1000 ,
b1000 "
b1100 -
05
04
03
12
b1100 6
0'
0&
1%
#730
b1001001 (
b1001001 *
b1001 ,
b1001 "
b1101 -
15
b1101 6
1'
#740
b1001010 (
b1001010 *
b1010 ,
b1010 "
b1110 -
05
14
b1110 6
0'
1&
#750
b1001011 (
b1001011 *
b1011 ,
b1011 "
b1111 -
15
b1111 6
1'
#760
b1001100 (
b1001100 *
b1100 ,
b1100 "
b10000 -
05
04
13
b10000 6
0'
0&
0%
0$
1#
#770
b1001101 (
b1001101 *
b1101 ,
b1101 "
b10001 -
15
b10001 6
1'
#780
b1001110 (
b1001110 *
b1110 ,
b1110 "
b10010 -
05
14
b10010 6
0'
1&
#790
b1001111 (
b1001111 *
b1111 ,
b1111 "
b10011 -
15
b10011 6
1'
#800
b1010000 (
b1010000 *
b10000 ,
b101 +
b0 ,
b101 !
b0 "
b101 -
05
04
03
02
11
b101 6
0&
1%
0#
#810
b1010001 (
b1010001 *
b1 ,
b1 "
b110 -
15
b110 6
0'
1&
#820
b1010010 (
b1010010 *
b10 ,
b10 "
b111 -
05
14
b111 6
1'
#830
b1010011 (
b1010011 *
b11 ,
b11 "
b1000 -
15
b1000 6
0'
0&
0%
1$
#840
b1010100 (
b1010100 *
b100 ,
b100 "
b1001 -
05
04
13
b1001 6
1'
#850
b1010101 (
b1010101 *
b101 ,
b101 "
b1010 -
15
b1010 6
0'
1&
#860
b1010110 (
b1010110 *
b110 ,
b110 "
b1011 -
05
14
b1011 6
1'
#870
b1010111 (
b1010111 *
b111 ,
b111 "
b1100 -
15
b1100 6
0'
0&
1%
#880
b1011000 (
b1011000 *
b1000 ,
b1000 "
b1101 -
05
04
03
12
b1101 6
1'
#890
b1011001 (
b1011001 *
b1001 ,
b1001 "
b1110 -
15
b1110 6
0'
1&
#900
b1011010 (
b1011010 *
b1010 ,
b1010 "
b1111 -
05
14
b1111 6
1'
#910
b1011011 (
b1011011 *
b1011 ,
b1011 "
b10000 -
15
b10000 6
0'
0&
0%
0$
1#
#920
b1011100 (
b1011100 *
b1100 ,
b1100 "
b10001 -
05
04
13
b10001 6
1'
#930
b1011101 (
b1011101 *
b1101 ,
b1101 "
b10010 -
15
b10010 6
0'
1&
#940
b1011110 (
b1011110 *
b1110 ,
b1110 "
b10011 -
05
14
b10011 6
1'
#950
b1011111 (
b1011111 *
b1111 ,
b1111 "
b10100 -
15
b10100 6
0'
0&
1%
#960
b1100000 (
b1100000 *
b10000 ,
b110 +
b0 ,
b110 !
b0 "
b110 -
05
04
03
02
01
10
b110 6
1&
0#
#970
b1100001 (
b1100001 *
b1 ,
b1 "
b111 -
15
b111 6
1'
#980
b1100010 (
b1100010 *
b10 ,
b10 "
b1000 -
05
14
b1000 6
0'
0&
0%
1$
#990
b1100011 (
b1100011 *
b11 ,
b11 "
b1001 -
15
b1001 6
1'
#1000
b1100100 (
b1100100 *
b100 ,
b100 "
b1010 -
05
04
13
b1010 6
0'
1&
#1010
b1100101 (
b1100101 *
b101 ,
b101 "
b1011 -
15
b1011 6
1'
#1020
b1100110 (
b1100110 *
b110 ,
b110 "
b1100 -
05
14
b1100 6
0'
0&
1%
#1030
b1100111 (
b1100111 *
b111 ,
b111 "
b1101 -
15
b1101 6
1'
#1040
b1101000 (
b1101000 *
b1000 ,
b1000 "
b1110 -
05
04
03
12
b1110 6
0'
1&
#1050
b1101001 (
b1101001 *
b1001 ,
b1001 "
b1111 -
15
b1111 6
1'
#1060
b1101010 (
b1101010 *
b1010 ,
b1010 "
b10000 -
05
14
b10000 6
0'
0&
0%
0$
1#
#1070
b1101011 (
b1101011 *
b1011 ,
b1011 "
b10001 -
15
b10001 6
1'
#1080
b1101100 (
b1101100 *
b1100 ,
b1100 "
b10010 -
05
04
13
b10010 6
0'
1&
#1090
b1101101 (
b1101101 *
b1101 ,
b1101 "
b10011 -
15
b10011 6
1'
#1100
b1101110 (
b1101110 *
b1110 ,
b1110 "
b10100 -
05
14
b10100 6
0'
0&
1%
#1110
b1101111 (
b1101111 *
b1111 ,
b1111 "
b10101 -
15
b10101 6
1'
#1120
b1110000 (
b1110000 *
b10000 ,
b111 +
b0 ,
b111 !
b0 "
b111 -
05
04
03
02
11
b111 6
1&
0#
#1130
b1110001 (
b1110001 *
b1 ,
b1 "
b1000 -
15
b1000 6
0'
0&
0%
1$
#1140
b1110010 (
b1110010 *
b10 ,
b10 "
b1001 -
05
14
b1001 6
1'
#1150
b1110011 (
b1110011 *
b11 ,
b11 "
b1010 -
15
b1010 6
0'
1&
#1160
b1110100 (
b1110100 *
b100 ,
b100 "
b1011 -
05
04
13
b1011 6
1'
#1170
b1110101 (
b1110101 *
b101 ,
b101 "
b1100 -
15
b1100 6
0'
0&
1%
#1180
b1110110 (
b1110110 *
b110 ,
b110 "
b1101 -
05
14
b1101 6
1'
#1190
b1110111 (
b1110111 *
b111 ,
b111 "
b1110 -
15
b1110 6
0'
1&
#1200
b1111000 (
b1111000 *
b1000 ,
b1000 "
b1111 -
05
04
03
12
b1111 6
1'
#1210
b1111001 (
b1111001 *
b1001 ,
b1001 "
b10000 -
15
b10000 6
0'
0&
0%
0$
1#
#1220
b1111010 (
b1111010 *
b1010 ,
b1010 "
b10001 -
05
14
b10001 6
1'
#1230
b1111011 (
b1111011 *
b1011 ,
b1011 "
b10010 -
15
b10010 6
0'
1&
#1240
b1111100 (
b1111100 *
b1100 ,
b1100 "
b10011 -
05
04
13
b10011 6
1'
#1250
b1111101 (
b1111101 *
b1101 ,
b1101 "
b10100 -
15
b10100 6
0'
0&
1%
#1260
b1111110 (
b1111110 *
b1110 ,
b1110 "
b10101 -
05
14
b10101 6
1'
#1270
b1111111 (
b1111111 *
b1111 ,
b1111 "
b10110 -
15
b10110 6
0'
1&
#1280
b10000000 (
b10000000 *
b10000 ,
b1000 +
b0 ,
b1000 !
b0 "
b1000 -
05
04
03
02
01
00
0/
1.
b1000 6
0&
0%
1$
0#
#1290
b10000001 (
b10000001 *
b1 ,
b1 "
b1001 -
15
b1001 6
1'
#1300
b10000010 (
b10000010 *
b10 ,
b10 "
b1010 -
05
14
b1010 6
0'
1&
#1310
b10000011 (
b10000011 *
b11 ,
b11 "
b1011 -
15
b1011 6
1'
#1320
b10000100 (
b10000100 *
b100 ,
b100 "
b1100 -
05
04
13
b1100 6
0'
0&
1%
#1330
b10000101 (
b10000101 *
b101 ,
b101 "
b1101 -
15
b1101 6
1'
#1340
b10000110 (
b10000110 *
b110 ,
b110 "
b1110 -
05
14
b1110 6
0'
1&
#1350
b10000111 (
b10000111 *
b111 ,
b111 "
b1111 -
15
b1111 6
1'
#1360
b10001000 (
b10001000 *
b1000 ,
b1000 "
b10000 -
05
04
03
12
b10000 6
0'
0&
0%
0$
1#
#1370
b10001001 (
b10001001 *
b1001 ,
b1001 "
b10001 -
15
b10001 6
1'
#1380
b10001010 (
b10001010 *
b1010 ,
b1010 "
b10010 -
05
14
b10010 6
0'
1&
#1390
b10001011 (
b10001011 *
b1011 ,
b1011 "
b10011 -
15
b10011 6
1'
#1400
b10001100 (
b10001100 *
b1100 ,
b1100 "
b10100 -
05
04
13
b10100 6
0'
0&
1%
#1410
b10001101 (
b10001101 *
b1101 ,
b1101 "
b10101 -
15
b10101 6
1'
#1420
b10001110 (
b10001110 *
b1110 ,
b1110 "
b10110 -
05
14
b10110 6
0'
1&
#1430
b10001111 (
b10001111 *
b1111 ,
b1111 "
b10111 -
15
b10111 6
1'
#1440
b10010000 (
b10010000 *
b10000 ,
b1001 +
b0 ,
b1001 !
b0 "
b1001 -
05
04
03
02
11
b1001 6
0&
0%
1$
0#
#1450
b10010001 (
b10010001 *
b1 ,
b1 "
b1010 -
15
b1010 6
0'
1&
#1460
b10010010 (
b10010010 *
b10 ,
b10 "
b1011 -
05
14
b1011 6
1'
#1470
b10010011 (
b10010011 *
b11 ,
b11 "
b1100 -
15
b1100 6
0'
0&
1%
#1480
b10010100 (
b10010100 *
b100 ,
b100 "
b1101 -
05
04
13
b1101 6
1'
#1490
b10010101 (
b10010101 *
b101 ,
b101 "
b1110 -
15
b1110 6
0'
1&
#1500
b10010110 (
b10010110 *
b110 ,
b110 "
b1111 -
05
14
b1111 6
1'
#1510
b10010111 (
b10010111 *
b111 ,
b111 "
b10000 -
15
b10000 6
0'
0&
0%
0$
1#
#1520
b10011000 (
b10011000 *
b1000 ,
b1000 "
b10001 -
05
04
03
12
b10001 6
1'
#1530
b10011001 (
b10011001 *
b1001 ,
b1001 "
b10010 -
15
b10010 6
0'
1&
#1540
b10011010 (
b10011010 *
b1010 ,
b1010 "
b10011 -
05
14
b10011 6
1'
#1550
b10011011 (
b10011011 *
b1011 ,
b1011 "
b10100 -
15
b10100 6
0'
0&
1%
#1560
b10011100 (
b10011100 *
b1100 ,
b1100 "
b10101 -
05
04
13
b10101 6
1'
#1570
b10011101 (
b10011101 *
b1101 ,
b1101 "
b10110 -
15
b10110 6
0'
1&
#1580
b10011110 (
b10011110 *
b1110 ,
b1110 "
b10111 -
05
14
b10111 6
1'
#1590
b10011111 (
b10011111 *
b1111 ,
b1111 "
b11000 -
15
b11000 6
0'
0&
0%
1$
#1600
b10100000 (
b10100000 *
b10000 ,
b1010 +
b0 ,
b1010 !
b0 "
b1010 -
05
04
03
02
01
10
b1010 6
1&
0#
#1610
b10100001 (
b10100001 *
b1 ,
b1 "
b1011 -
15
b1011 6
1'
#1620
b10100010 (
b10100010 *
b10 ,
b10 "
b1100 -
05
14
b1100 6
0'
0&
1%
#1630
b10100011 (
b10100011 *
b11 ,
b11 "
b1101 -
15
b1101 6
1'
#1640
b10100100 (
b10100100 *
b100 ,
b100 "
b1110 -
05
04
13
b1110 6
0'
1&
#1650
b10100101 (
b10100101 *
b101 ,
b101 "
b1111 -
15
b1111 6
1'
#1660
b10100110 (
b10100110 *
b110 ,
b110 "
b10000 -
05
14
b10000 6
0'
0&
0%
0$
1#
#1670
b10100111 (
b10100111 *
b111 ,
b111 "
b10001 -
15
b10001 6
1'
#1680
b10101000 (
b10101000 *
b1000 ,
b1000 "
b10010 -
05
04
03
12
b10010 6
0'
1&
#1690
b10101001 (
b10101001 *
b1001 ,
b1001 "
b10011 -
15
b10011 6
1'
#1700
b10101010 (
b10101010 *
b1010 ,
b1010 "
b10100 -
05
14
b10100 6
0'
0&
1%
#1710
b10101011 (
b10101011 *
b1011 ,
b1011 "
b10101 -
15
b10101 6
1'
#1720
b10101100 (
b10101100 *
b1100 ,
b1100 "
b10110 -
05
04
13
b10110 6
0'
1&
#1730
b10101101 (
b10101101 *
b1101 ,
b1101 "
b10111 -
15
b10111 6
1'
#1740
b10101110 (
b10101110 *
b1110 ,
b1110 "
b11000 -
05
14
b11000 6
0'
0&
0%
1$
#1750
b10101111 (
b10101111 *
b1111 ,
b1111 "
b11001 -
15
b11001 6
1'
#1760
b10110000 (
b10110000 *
b10000 ,
b1011 +
b0 ,
b1011 !
b0 "
b1011 -
05
04
03
02
11
b1011 6
1&
0#
#1770
b10110001 (
b10110001 *
b1 ,
b1 "
b1100 -
15
b1100 6
0'
0&
1%
#1780
b10110010 (
b10110010 *
b10 ,
b10 "
b1101 -
05
14
b1101 6
1'
#1790
b10110011 (
b10110011 *
b11 ,
b11 "
b1110 -
15
b1110 6
0'
1&
#1800
b10110100 (
b10110100 *
b100 ,
b100 "
b1111 -
05
04
13
b1111 6
1'
#1810
b10110101 (
b10110101 *
b101 ,
b101 "
b10000 -
15
b10000 6
0'
0&
0%
0$
1#
#1820
b10110110 (
b10110110 *
b110 ,
b110 "
b10001 -
05
14
b10001 6
1'
#1830
b10110111 (
b10110111 *
b111 ,
b111 "
b10010 -
15
b10010 6
0'
1&
#1840
b10111000 (
b10111000 *
b1000 ,
b1000 "
b10011 -
05
04
03
12
b10011 6
1'
#1850
b10111001 (
b10111001 *
b1001 ,
b1001 "
b10100 -
15
b10100 6
0'
0&
1%
#1860
b10111010 (
b10111010 *
b1010 ,
b1010 "
b10101 -
05
14
b10101 6
1'
#1870
b10111011 (
b10111011 *
b1011 ,
b1011 "
b10110 -
15
b10110 6
0'
1&
#1880
b10111100 (
b10111100 *
b1100 ,
b1100 "
b10111 -
05
04
13
b10111 6
1'
#1890
b10111101 (
b10111101 *
b1101 ,
b1101 "
b11000 -
15
b11000 6
0'
0&
0%
1$
#1900
b10111110 (
b10111110 *
b1110 ,
b1110 "
b11001 -
05
14
b11001 6
1'
#1910
b10111111 (
b10111111 *
b1111 ,
b1111 "
b11010 -
15
b11010 6
0'
1&
#1920
b11000000 (
b11000000 *
b10000 ,
b1100 +
b0 ,
b1100 !
b0 "
b1100 -
05
04
03
02
01
00
1/
b1100 6
0&
1%
0#
#1930
b11000001 (
b11000001 *
b1 ,
b1 "
b1101 -
15
b1101 6
1'
#1940
b11000010 (
b11000010 *
b10 ,
b10 "
b1110 -
05
14
b1110 6
0'
1&
#1950
b11000011 (
b11000011 *
b11 ,
b11 "
b1111 -
15
b1111 6
1'
#1960
b11000100 (
b11000100 *
b100 ,
b100 "
b10000 -
05
04
13
b10000 6
0'
0&
0%
0$
1#
#1970
b11000101 (
b11000101 *
b101 ,
b101 "
b10001 -
15
b10001 6
1'
#1980
b11000110 (
b11000110 *
b110 ,
b110 "
b10010 -
05
14
b10010 6
0'
1&
#1990
b11000111 (
b11000111 *
b111 ,
b111 "
b10011 -
15
b10011 6
1'
#2000
b11001000 (
b11001000 *
b1000 ,
b1000 "
b10100 -
05
04
03
12
b10100 6
0'
0&
1%
#2010
b11001001 (
b11001001 *
b1001 ,
b1001 "
b10101 -
15
b10101 6
1'
#2020
b11001010 (
b11001010 *
b1010 ,
b1010 "
b10110 -
05
14
b10110 6
0'
1&
#2030
b11001011 (
b11001011 *
b1011 ,
b1011 "
b10111 -
15
b10111 6
1'
#2040
b11001100 (
b11001100 *
b1100 ,
b1100 "
b11000 -
05
04
13
b11000 6
0'
0&
0%
1$
#2050
b11001101 (
b11001101 *
b1101 ,
b1101 "
b11001 -
15
b11001 6
1'
#2060
b11001110 (
b11001110 *
b1110 ,
b1110 "
b11010 -
05
14
b11010 6
0'
1&
#2070
b11001111 (
b11001111 *
b1111 ,
b1111 "
b11011 -
15
b11011 6
1'
#2080
b11010000 (
b11010000 *
b10000 ,
b1101 +
b0 ,
b1101 !
b0 "
b1101 -
05
04
03
02
11
b1101 6
0&
1%
0#
#2090
b11010001 (
b11010001 *
b1 ,
b1 "
b1110 -
15
b1110 6
0'
1&
#2100
b11010010 (
b11010010 *
b10 ,
b10 "
b1111 -
05
14
b1111 6
1'
#2110
b11010011 (
b11010011 *
b11 ,
b11 "
b10000 -
15
b10000 6
0'
0&
0%
0$
1#
#2120
b11010100 (
b11010100 *
b100 ,
b100 "
b10001 -
05
04
13
b10001 6
1'
#2130
b11010101 (
b11010101 *
b101 ,
b101 "
b10010 -
15
b10010 6
0'
1&
#2140
b11010110 (
b11010110 *
b110 ,
b110 "
b10011 -
05
14
b10011 6
1'
#2150
b11010111 (
b11010111 *
b111 ,
b111 "
b10100 -
15
b10100 6
0'
0&
1%
#2160
b11011000 (
b11011000 *
b1000 ,
b1000 "
b10101 -
05
04
03
12
b10101 6
1'
#2170
b11011001 (
b11011001 *
b1001 ,
b1001 "
b10110 -
15
b10110 6
0'
1&
#2180
b11011010 (
b11011010 *
b1010 ,
b1010 "
b10111 -
05
14
b10111 6
1'
#2190
b11011011 (
b11011011 *
b1011 ,
b1011 "
b11000 -
15
b11000 6
0'
0&
0%
1$
#2200
b11011100 (
b11011100 *
b1100 ,
b1100 "
b11001 -
05
04
13
b11001 6
1'
#2210
b11011101 (
b11011101 *
b1101 ,
b1101 "
b11010 -
15
b11010 6
0'
1&
#2220
b11011110 (
b11011110 *
b1110 ,
b1110 "
b11011 -
05
14
b11011 6
1'
#2230
b11011111 (
b11011111 *
b1111 ,
b1111 "
b11100 -
15
b11100 6
0'
0&
1%
#2240
b11100000 (
b11100000 *
b10000 ,
b1110 +
b0 ,
b1110 !
b0 "
b1110 -
05
04
03
02
01
10
b1110 6
1&
0#
#2250
b11100001 (
b11100001 *
b1 ,
b1 "
b1111 -
15
b1111 6
1'
#2260
b11100010 (
b11100010 *
b10 ,
b10 "
b10000 -
05
14
b10000 6
0'
0&
0%
0$
1#
#2270
b11100011 (
b11100011 *
b11 ,
b11 "
b10001 -
15
b10001 6
1'
#2280
b11100100 (
b11100100 *
b100 ,
b100 "
b10010 -
05
04
13
b10010 6
0'
1&
#2290
b11100101 (
b11100101 *
b101 ,
b101 "
b10011 -
15
b10011 6
1'
#2300
b11100110 (
b11100110 *
b110 ,
b110 "
b10100 -
05
14
b10100 6
0'
0&
1%
#2310
b11100111 (
b11100111 *
b111 ,
b111 "
b10101 -
15
b10101 6
1'
#2320
b11101000 (
b11101000 *
b1000 ,
b1000 "
b10110 -
05
04
03
12
b10110 6
0'
1&
#2330
b11101001 (
b11101001 *
b1001 ,
b1001 "
b10111 -
15
b10111 6
1'
#2340
b11101010 (
b11101010 *
b1010 ,
b1010 "
b11000 -
05
14
b11000 6
0'
0&
0%
1$
#2350
b11101011 (
b11101011 *
b1011 ,
b1011 "
b11001 -
15
b11001 6
1'
#2360
b11101100 (
b11101100 *
b1100 ,
b1100 "
b11010 -
05
04
13
b11010 6
0'
1&
#2370
b11101101 (
b11101101 *
b1101 ,
b1101 "
b11011 -
15
b11011 6
1'
#2380
b11101110 (
b11101110 *
b1110 ,
b1110 "
b11100 -
05
14
b11100 6
0'
0&
1%
#2390
b11101111 (
b11101111 *
b1111 ,
b1111 "
b11101 -
15
b11101 6
1'
#2400
b11110000 (
b11110000 *
b10000 ,
b1111 +
b0 ,
b1111 !
b0 "
b1111 -
05
04
03
02
11
b1111 6
1&
0#
#2410
b11110001 (
b11110001 *
b1 ,
b1 "
b10000 -
15
b10000 6
0'
0&
0%
0$
1#
#2420
b11110010 (
b11110010 *
b10 ,
b10 "
b10001 -
05
14
b10001 6
1'
#2430
b11110011 (
b11110011 *
b11 ,
b11 "
b10010 -
15
b10010 6
0'
1&
#2440
b11110100 (
b11110100 *
b100 ,
b100 "
b10011 -
05
04
13
b10011 6
1'
#2450
b11110101 (
b11110101 *
b101 ,
b101 "
b10100 -
15
b10100 6
0'
0&
1%
#2460
b11110110 (
b11110110 *
b110 ,
b110 "
b10101 -
05
14
b10101 6
1'
#2470
b11110111 (
b11110111 *
b111 ,
b111 "
b10110 -
15
b10110 6
0'
1&
#2480
b11111000 (
b11111000 *
b1000 ,
b1000 "
b10111 -
05
04
03
12
b10111 6
1'
#2490
b11111001 (
b11111001 *
b1001 ,
b1001 "
b11000 -
15
b11000 6
0'
0&
0%
1$
#2500
b11111010 (
b11111010 *
b1010 ,
b1010 "
b11001 -
05
14
b11001 6
1'
#2510
b11111011 (
b11111011 *
b1011 ,
b1011 "
b11010 -
15
b11010 6
0'
1&
#2520
b11111100 (
b11111100 *
b1100 ,
b1100 "
b11011 -
05
04
13
b11011 6
1'
#2530
b11111101 (
b11111101 *
b1101 ,
b1101 "
b11100 -
15
b11100 6
0'
0&
1%
#2540
b11111110 (
b11111110 *
b1110 ,
b1110 "
b11101 -
05
14
b11101 6
1'
#2550
b11111111 (
b11111111 *
b1111 ,
b1111 "
b11110 -
15
b11110 6
0'
1&
#2560
b100000000 (
b100000000 *
b10000 ,
b10000 +
