Waqar/tasks/shift_register/shift_reg.sv
module shift_reg_4b(input logic clk_i, rst_i,
                    input logic d_i,
                    output logic q_o);

        logic [3:0] shift_reg;
        int i;
        
        always_ff @(posedge clk_i) begin
            if(~rst_i) begin
                shift_reg <= 4'b0000;
            end
            else begin
                shift_reg [3] <= shift_reg [2];
                shift_reg [2] <= shift_reg [1];
                shift_reg [1] <= shift_reg [0];
                shift_reg [0] <= d_i;
            end
        end

            

        assign q_o = shift_reg[3];
        
endmodule

Waqar/tasks/shift_register/shift_reg_tb.sv
module shift_reg_tb;

    reg clk_i;
    reg rst_i;
    reg d_i;
    wire q_o;

    initial begin
        clk_i = 1;
        forever #10 clk_i = ~clk_i;
    end

    shift_reg_4b dut (
        .clk_i(clk_i), 
        .rst_i(rst_i),
        .d_i(d_i),
        .q_o(q_o)
    );

    initial begin
        rst_i = 0;
        d_i = 0;
        #10;
        rst_i = 1;
        @(posedge clk_i)d_i = 1'b1;
        @(posedge clk_i)d_i = 1'b0;
        @(posedge clk_i)d_i = 1'b1;
        //#10;
        //d_i = 3'b111;
        
        #100;
        $finish;
    end

    initial begin
        $dumpfile("reg.vcd");
        $dumpvars(0, shift_reg_tb);
    end

endmodule

Waqar/tasks/shift_register/reg.vcd
$date
	Sat Jul 13 13:55:00 2024
$end
$version
	ModelSim Version 2020.1
$end
$timescale
	1ps
$end

$scope module shift_reg_tb $end
$var reg 1 ! clk_i $end
$var reg 1 " rst_i $end
$var reg 1 # d_i $end
$var wire 1 $ q_o $end

$scope module dut $end
$var wire 1 % clk_i $end
$var wire 1 & rst_i $end
$var wire 1 ' d_i $end
$var reg 1 ( q_o $end
$var reg 4 ) shift_reg [3:0] $end
$var integer 32 * i $end
$upscope $end
$upscope $end
$enddefinitions $end
#0
$dumpvars
1!
0"
0#
0(
b0 )
b0 *
0$
1%
0&
0'
$end
#10
0!
1"
1&
0%
#20
1!
1%
1#
1'
#30
0!
0%
#40
1!
1%
0#
0'
b1 )
#50
0!
0%
#60
1!
1%
1#
1'
b11 )
b10 )
#70
0!
0%
#80
1!
1%
b110 )
b100 )
b101 )
#90
0!
0%
#100
1!
1%
b1101 )
b1001 )
b1011 )
1(
1$
#110
0!
0%
#120
1!
1%
b11 )
b111 )
0(
0$
#130
0!
0%
#140
1!
1%
b1111 )
1(
1$
