Waqar/tasks/alu_16b/alu_16b.sv
module alu_16b(input logic [15:0] a_i,b_i,
               input logic [2:0] alu_ctrl_i,
               output logic [16:0] c_o);
    
    always @* begin
        case(alu_ctrl_i)
            3'b000: c_o = a_i + b_i;
            3'b001: c_o = a_i - b_i;
            3'b010: c_o = a_i & b_i;
            3'b011: c_o = a_i | b_i;
            3'b100: c_o = a_i ^ b_i; 
            default: c_o = a_i + b_i;
        endcase
    end

endmodule

Waqar/tasks/alu_16b/alu_16b_tb.sv
module alu_16b_tb;

    logic [15:0] a_i, b_i;
    logic [2:0]  alu_ctrl_i;
    logic [16:0] c_o;
    logic [16:0] c_expected;

    parameter int TEST_SIZE = 100; 
    int correct_check = 0;
    int incorrect_check = 0;
    int total_checks = 0;

    // Individual operation counters
    int add_correct = 0, add_incorrect = 0;
    int sub_correct = 0, sub_incorrect = 0;
    int and_correct = 0, and_incorrect = 0;
    int or_correct = 0, or_incorrect = 0;
    int xor_correct = 0, xor_incorrect = 0;

    alu_16b dut (.a_i(a_i), .b_i(b_i), .alu_ctrl_i(alu_ctrl_i), .c_o(c_o));

    // Task to generate stimulus
    task generator_task(input int test_num, input logic [2:0] alu_ctrl);
        string operation;
        begin
            a_i = $urandom;
            b_i = $urandom;
            case (alu_ctrl)
                3'b000: begin
                    c_expected = a_i + b_i;
                    operation = "ADD";
                end
                3'b001: begin
                    c_expected = a_i - b_i;
                    operation = "SUB";
                end
                3'b010: begin
                    c_expected = a_i & b_i;
                    operation = "AND";
                end
                3'b011: begin
                    c_expected = a_i | b_i;
                    operation = "OR";
                end
                3'b100: begin
                    c_expected = a_i ^ b_i;
                    operation = "XOR";
                end
                default: begin
                    c_expected = a_i + b_i;
                    operation = "DEFAULT (ADD)";
                end
            endcase
            $display("Test %d: Operation = %s, a = %d, b = %d, expected = %d", test_num, operation, a_i, b_i, c_expected);
        end
    endtask

    // Task to monitor and check results
    task monitor_task(input int test_num, input logic [2:0] alu_ctrl);
        string operation;
        begin
            #10; // Wait for some time to simulate the delay
            case (alu_ctrl)
                3'b000: operation = "ADD";
                3'b001: operation = "SUB";
                3'b010: operation = "AND";
                3'b011: operation = "OR";
                3'b100: operation = "XOR";
                default: operation = "DEFAULT (ADD)";
            endcase

            if (c_o == c_expected) begin
                $display("Check %d -> Passed: Operation = %s, a = %d, b = %d, c = %d, expected = %d", test_num, operation, a_i, b_i, c_o, c_expected);
                correct_check++;
                case (alu_ctrl)
                    3'b000: add_correct++;
                    3'b001: sub_correct++;
                    3'b010: and_correct++;
                    3'b011: or_correct++;
                    3'b100: xor_correct++;
                endcase
            end else begin
                $display("Check %d -> Failed: Operation = %s, a = %d, b = %d, c = %d, expected = %d", test_num, operation, a_i, b_i, c_o, c_expected);
                incorrect_check++;
                case (alu_ctrl)
                    3'b000: add_incorrect++;
                    3'b001: sub_incorrect++;
                    3'b010: and_incorrect++;
                    3'b011: or_incorrect++;
                    3'b100: xor_incorrect++;
                endcase
            end
            total_checks++;
        end
    endtask

    initial begin
        for (alu_ctrl_i = 0; alu_ctrl_i < 5; alu_ctrl_i++) begin
            for (int i = 0; i < TEST_SIZE; i++) begin
                generator_task(i, alu_ctrl_i);
                monitor_task(i, alu_ctrl_i);
            end
        end
        $display("Total checks: %d, Passed: %d, Failed: %d", total_checks, correct_check, incorrect_check);
        $display("Operation-wise results:");
        $display("ADD Passed: %d, Failed: %d", add_correct, add_incorrect);
        $display("SUB Passed: %d, Failed: %d", sub_correct, sub_incorrect);
        $display("AND Passed: %d, Failed: %d", and_correct, and_incorrect);
        $display("OR Passed: %d, Failed: %d", or_correct, or_incorrect);
        $display("XOR Passed: %d, Failed: %d", xor_correct, xor_incorrect);
    end

    initial begin
        $dumpfile("alu_16b_tb.vcd");
        $dumpvars(0, alu_16b_tb);
    end

endmodule

Waqar/tasks/alu_16b/alu_16b_tb.vcd
$date
	Sat Jul 13 13:20:57 2024
$end
$version
	ModelSim Version 2020.1
$end
$timescale
	1ps
$end

$scope module alu_16b_tb $end
$var parameter 32 ! TEST_SIZE $end
$var reg 16 " a_i [15:0] $end
$var reg 16 # b_i [15:0] $end
$var reg 3 $ alu_ctrl_i [2:0] $end
$var reg 17 % c_o [16:0] $end
$var reg 17 & c_expected [16:0] $end
$var integer 32 ' correct_check $end
$var integer 32 ( incorrect_check $end
$var integer 32 ) total_checks $end
$var integer 32 * add_correct $end
$var integer 32 + add_incorrect $end
$var integer 32 , sub_correct $end
$var integer 32 - sub_incorrect $end
$var integer 32 . and_correct $end
$var integer 32 / and_incorrect $end
$var integer 32 0 or_correct $end
$var integer 32 1 or_incorrect $end
$var integer 32 2 xor_correct $end
$var integer 32 3 xor_incorrect $end

$scope task generator_task $end
$var integer 32 4 test_num $end
$var reg 3 5 alu_ctrl [2:0] $end
$upscope $end

$scope task monitor_task $end
$var integer 32 6 test_num $end
$var reg 3 7 alu_ctrl [2:0] $end
$upscope $end

$scope module dut $end
$var wire 1 8 a_i [15] $end
$var wire 1 9 a_i [14] $end
$var wire 1 : a_i [13] $end
$var wire 1 ; a_i [12] $end
$var wire 1 < a_i [11] $end
$var wire 1 = a_i [10] $end
$var wire 1 > a_i [9] $end
$var wire 1 ? a_i [8] $end
$var wire 1 @ a_i [7] $end
$var wire 1 A a_i [6] $end
$var wire 1 B a_i [5] $end
$var wire 1 C a_i [4] $end
$var wire 1 D a_i [3] $end
$var wire 1 E a_i [2] $end
$var wire 1 F a_i [1] $end
$var wire 1 G a_i [0] $end
$var wire 1 H b_i [15] $end
$var wire 1 I b_i [14] $end
$var wire 1 J b_i [13] $end
$var wire 1 K b_i [12] $end
$var wire 1 L b_i [11] $end
$var wire 1 M b_i [10] $end
$var wire 1 N b_i [9] $end
$var wire 1 O b_i [8] $end
$var wire 1 P b_i [7] $end
$var wire 1 Q b_i [6] $end
$var wire 1 R b_i [5] $end
$var wire 1 S b_i [4] $end
$var wire 1 T b_i [3] $end
$var wire 1 U b_i [2] $end
$var wire 1 V b_i [1] $end
$var wire 1 W b_i [0] $end
$var wire 1 X alu_ctrl_i [2] $end
$var wire 1 Y alu_ctrl_i [1] $end
$var wire 1 Z alu_ctrl_i [0] $end
$var reg 17 [ c_o [16:0] $end
$upscope $end
$upscope $end
$enddefinitions $end
#0
$dumpvars
b1010001110111000 "
b110000100110 #
b0 $
b1010111111011110 %
b1010111111011110 &
b1010111111011110 [
b0 5
b0 7
b1100100 !
b0 '
b0 (
b0 )
b0 *
b0 +
b0 ,
b0 -
b0 .
b0 /
b0 0
b0 1
b0 2
b0 3
b0 4
b0 6
0G
0F
0E
1D
1C
1B
0A
1@
1?
1>
0=
0<
0;
1:
09
18
0W
1V
1U
0T
0S
1R
0Q
0P
0O
0N
1M
1L
0K
0J
0I
0H
0Z
0Y
0X
$end
#10
b1 '
b1 *
b1 )
b1 4
b1011100101100110 "
b1110001110110110 #
b11001110100011100 &
b1 6
1S
1P
1O
1N
0M
0L
1J
1I
1H
1F
1E
0D
0C
1A
0@
0>
1<
1;
b11001110100011100 [
b11001110100011100 %
#20
b10 '
b10 *
b10 )
b10 4
b100011000110 "
b110111001000110 #
b111011100001100 &
b10 6
0S
0R
1Q
0P
0O
1M
1L
0H
0B
1@
0?
0;
0:
08
b111011100001100 [
b111011100001100 %
#30
b11 '
b11 *
b11 )
b11 4
b111101110010 "
b1111001100101110 #
b10000001010100000 &
b11 6
1T
1R
0Q
1O
0M
0L
1K
1H
0E
1C
1B
0@
1?
1>
1=
b10000001010100000 [
b10000001010100000 %
#40
b100 '
b100 *
b100 )
b100 4
b100010001100111 "
b101010100111010 #
b1001100110100001 &
b100 6
0U
1S
0N
1M
0J
0H
1G
1E
0C
0?
0>
0<
19
b1001100110100001 [
b1001100110100001 %
#50
b101 '
b101 *
b101 )
b101 4
b1110001101010 "
b1101000110110100 #
b1110111000011110 &
b101 6
0V
1U
0T
1P
0M
1H
0G
0E
1D
1<
1;
09
b1110111000011110 [
b1110111000011110 %
#60
b110 '
b110 *
b110 )
b110 4
b1111101001101111 "
b1101001010110 #
b10001010011000101 &
b110 6
1V
0R
1Q
0P
0O
1N
1L
0I
0H
1G
1E
1>
0=
1:
19
18
b10001010011000101 [
b10001010011000101 %
#70
b111 '
b111 *
b111 )
b111 4
b11011000110101 "
b111011111010100 #
b1010111000001001 &
b111 6
0V
1P
1O
1M
0L
1J
1I
0F
0D
1C
0A
1=
0<
09
08
b1010111000001001 [
b1010111000001001 %
#80
b1000 '
b1000 *
b1000 )
b1000 4
b100000010101110 "
b1000000101111101 #
b1100001000101011 &
b1000 6
1W
1T
1R
0P
0N
0M
0K
0J
0I
1H
0G
1F
1D
0C
1@
0>
0=
0;
0:
19
b1100001000101011 [
b1100001000101011 %
#90
b1001 '
b1001 *
b1001 )
b1001 4
b1011011111011011 "
b111000000101 #
b1100010111100000 &
b1001 6
0T
0S
0R
0Q
0O
1N
1M
1L
0H
1G
0E
1C
0B
1A
1?
1>
1=
1;
1:
09
18
b1100010111100000 [
b1100010111100000 %
#100
b1010 '
b1010 *
b1010 )
b1010 4
b1000011011100011 "
b1000001100100000 #
b10000101000000011 &
b1010 6
0W
0U
1R
1O
0M
0L
1H
0D
0C
1B
0?
0;
0:
b10000101000000011 [
b10000101000000011 %
#110
b1011 '
b1011 *
b1011 )
b1011 4
b110010111100101 "
b111011100000101 #
b1101110011101010 &
b1011 6
1W
1U
0R
1M
1K
1J
1I
0H
0F
1E
1?
0>
1:
19
08
b1101110011101010 [
b1101110011101010 %
#120
b1100 '
b1100 *
b1100 )
b1100 4
b1000110100100101 "
b1111011101001 #
b1010110000001110 &
b1100 6
0U
1T
1R
1Q
1P
0O
1L
0J
0I
0A
0@
1<
0:
09
18
b1010110000001110 [
b1010110000001110 %
#130
b1101 '
b1101 *
b1101 )
b1101 4
b10010001011101 "
b1001110110001010 #
b1100000111100111 &
b1101 6
0W
1V
0R
0Q
1O
0N
1H
1D
1C
0B
1A
0?
0<
1:
08
b1100000111100111 [
b1100000111100111 %
#140
b1110 '
b1110 *
b1110 )
b1110 4
b10000101011000 "
b100100110001011 #
b110101011100011 &
b1110 6
1W
0M
0K
1I
0H
0G
0E
1?
0=
b110101011100011 [
b110101011100011 %
#150
b1111 '
b1111 *
b1111 )
b1111 4
b1101000101010110 "
b1001001111001001 #
b10110010100011111 &
b1111 6
0V
1Q
1N
0L
1K
0I
1H
1F
1E
0D
1;
0:
19
18
b10110010100011111 [
b10110010100011111 %
#160
b10000 '
b10000 *
b10000 )
b10000 4
b111001010111001 "
b1011000101000000 #
b10010001111111001 &
b10000 6
0W
0T
0P
0N
1J
1G
0F
0E
1D
1B
0A
1@
0?
1>
1:
08
b10010001111111001 [
b10010001111111001 %
#170
b10001 '
b10001 *
b10001 )
b10001 4
b1101011110000000 "
b1011111000001110 #
b11001010110001110 &
b10001 6
1V
1U
1T
0Q
0O
1N
1M
1L
0G
0D
0C
0B
1?
1=
0:
18
b11001010110001110 [
b11001010110001110 %
#180
b10010 '
b10010 *
b10010 )
b10010 4
b1100100011010100 "
b1110100110001110 #
b11011001001100010 &
b10010 6
1P
1O
0N
0M
0K
1I
1E
1C
1A
0?
0>
0=
1<
0;
b11011001001100010 [
b11011001001100010 %
#190
b10011 '
b10011 *
b10011 )
b10011 4
b110010011000000 "
b1100110010111 #
b111111001010111 &
b10011 6
1W
0T
1S
1K
0J
0I
0H
0E
0C
1=
0<
1:
08
b111111001010111 [
b111111001010111 %
#200
b10100 '
b10100 *
b10100 )
b10100 4
b1001000100100101 "
b1101101111000111 #
b10110110011101100 &
b10100 6
0S
1Q
1N
1I
1H
1G
1E
1B
0A
0@
1?
0=
1;
0:
09
18
b10110110011101100 [
b10110110011101100 %
#210
b10101 '
b10101 *
b10101 )
b10101 4
b111001001011000 "
b1111100101010001 #
b10110101110101001 &
b10101 6
0V
0U
1S
0P
0N
1J
0G
0E
1D
1C
0B
1A
0?
1>
1:
19
08
b10110101110101001 [
b10110101110101001 %
#220
b10110 '
b10110 *
b10110 )
b10110 4
b1100100100110010 "
b1101111000100011 #
b11010011101010101 &
b10110 6
1V
0S
1R
0Q
0O
1N
1M
0J
1F
0D
1B
0A
1?
0>
1<
0;
0:
18
b11010011101010101 [
b11010011101010101 %
#230
b10111 '
b10111 *
b10111 )
b10111 4
b1101001101010100 "
b110110011 #
b1101010100000111 &
b10111 6
1S
1P
1O
0N
0M
0L
0K
0I
0H
0F
1E
0B
1A
1>
0<
1;
b1101010100000111 [
b1101010100000111 %
#240
b11000 '
b11000 *
b11000 )
b11000 4
b101011001011010 "
b1101011100110 #
b111000101000000 &
b11000 6
0W
1U
0S
1Q
0O
1N
1L
1K
1F
0E
1D
0?
1=
08
b111000101000000 [
b111000101000000 %
#250
b11001 '
b11001 *
b11001 )
b11001 4
b1111010111110110 "
b11001001100101 #
b10010100001011011 &
b11001 6
1W
0V
0P
0L
1J
1E
0D
1B
1@
1?
0>
1:
18
b10010100001011011 [
b10010100001011011 %
#260
b11010 '
b11010 *
b11010 )
b11010 4
b1010111101010 "
b101101100001111 #
b111000011111001 &
b11010 6
1V
1T
0R
0Q
1O
1L
0J
1I
0E
1D
0C
0:
09
08
b111000011111001 [
b111000011111001 %
#270
b11011 '
b11011 *
b11011 )
b11011 4
b1000011101111 "
b1010010001000100 #
b1011010100110011 &
b11011 6
0W
0V
0T
1Q
0O
0N
1M
0L
0K
1J
0I
1H
1G
1E
0?
0=
b1011010100110011 [
b1011010100110011 %
#280
b11100 '
b11100 *
b11100 )
b11100 4
b101110111001001 "
b1000011001011 #
b110111010010100 &
b11100 6
1W
1V
0U
1T
1P
0M
1K
0J
0H
0F
0E
0B
1?
1=
1<
19
b110111010010100 [
b110111010010100 %
#290
b11101 '
b11101 *
b11101 )
b11101 4
b1100001101000111 "
b111101011000111 #
b10011111000001110 &
b11101 6
1U
0T
1N
1L
1J
1I
1F
1E
0D
0@
1>
0=
0<
0;
18
b10011111000001110 [
b10011111000001110 %
#300
b11110 '
b11110 *
b11110 )
b11110 4
b1101010111110010 "
b1001101111100001 #
b10111000111010011 &
b11110 6
0V
0U
1R
1O
0J
0I
1H
0G
0E
1C
1B
1@
0>
1=
1;
b10111000111010011 [
b10111000111010011 %
#310
b11111 '
b11111 *
b11111 )
b11111 4
b101001110000101 "
b1101001100110000 #
b10010011010110101 &
b11111 6
0W
1S
0Q
0P
0L
1I
1G
0F
1E
0C
0B
0A
1>
0=
08
b10010011010110101 [
b10010011010110101 %
#320
b100000 '
b100000 *
b100000 )
b100000 4
b10001001110110 "
b100100100011101 #
b110101110010011 &
b100000 6
1W
1U
1T
0R
0N
1L
0K
0H
0G
1F
1C
1B
1A
0@
0?
0;
1:
09
b110101110010011 [
b110101110010011 %
#330
b100001 '
b100001 *
b100001 )
b100001 4
b100010111010010 "
b1110011100010110 #
b10010110011101000 &
b100001 6
0W
1V
0T
1N
1M
0L
1J
1H
0E
0B
1@
1?
0>
1=
0:
19
b10010110011101000 [
b10010110011101000 %
#340
b100010 '
b100010 *
b100010 )
b100010 4
b111011011011 "
b1001101000000 #
b10001000011011 &
b100010 6
0V
0U
0S
1Q
0M
1K
0J
0I
0H
1G
1D
0?
1>
1<
09
b10001000011011 [
b10001000011011 %
#350
b100011 '
b100011 *
b100011 )
b100011 4
b1100101010110101 "
b11001010010001 #
b1111110101000110 &
b100011 6
1W
1S
0Q
1P
0O
1J
0F
1E
0D
1B
0A
0=
19
18
b1111110101000110 [
b1111110101000110 %
#360
b100100 '
b100100 *
b100100 )
b100100 4
b1001111101110011 "
b1000010100000 #
b1011000000010011 &
b100100 6
0W
0S
1R
0N
0J
1F
0E
1A
0@
1?
1=
1;
09
b1011000000010011 [
b1011000000010011 %
#370
b100101 '
b100101 *
b100101 )
b100101 4
b111110101010111 "
b1110000011101 #
b1001100101110100 &
b100101 6
1W
1U
1T
1S
0R
0P
1M
1L
1E
0B
0>
1:
19
08
b1001100101110100 [
b1001100101110100 %
#380
b100110 '
b100110 *
b100110 )
b100110 4
b1010001111010100 "
b1111111011101 #
b1100001110110001 &
b100110 6
1Q
1P
1O
1N
0G
0F
1@
1>
0=
0<
0;
09
18
b1100001110110001 [
b1100001110110001 %
#390
b100111 '
b100111 *
b100111 )
b100111 4
b1010000110011010 "
b1101000010000100 #
b10111001000011110 &
b100111 6
0W
0T
0S
0Q
0O
0N
0M
0L
1I
1H
1F
0E
1D
0A
0>
b10111001000011110 [
b10111001000011110 %
#400
b101000 '
b101000 *
b101000 )
b101000 4
b100101110110111 "
b1011110010001001 #
b10000100001000000 &
b101000 6
1W
0U
1T
1M
1L
1J
0I
1G
1E
0D
1B
1>
1<
0:
19
08
b10000100001000000 [
b10000100001000000 %
#410
b101001 '
b101001 *
b101001 )
b101001 4
b1001100100001010 "
b111101011010101 #
b10001001111011111 &
b101001 6
1U
0T
1S
1Q
1N
0M
1I
0H
0G
0E
1D
0C
0B
0@
0>
1;
09
18
b10001001111011111 [
b10001001111011111 %
#420
b101010 '
b101010 *
b101010 )
b101010 4
b110011111110 "
b11111001001100 #
b100101101001010 &
b101010 6
0W
1T
0S
0P
1M
0I
1E
1C
1B
1A
1@
0?
1=
0;
08
b100101101001010 [
b100101101001010 %
#430
b101011 '
b101011 *
b101011 )
b101011 4
b1000110111111110 "
b1101011000011 #
b1010100011000001 &
b101011 6
1W
1V
0U
0T
1P
0M
0J
1?
18
b1010100011000001 [
b1010100011000001 %
#440
b101100 '
b101100 *
b101100 )
b101100 4
b1110111110001000 "
b1110110111100 #
b10000110101000100 &
b101100 6
0W
0V
1U
1T
1S
1R
0Q
1O
0N
1M
0F
0E
0C
0B
0A
1>
1:
19
b10000110101000100 [
b10000110101000100 %
#450
b101101 '
b101101 *
b101101 )
b101101 4
b100010110011011 "
b1011101011110011 #
b10000000010001110 &
b101101 6
1W
1V
0U
0T
1Q
0O
1N
0M
1J
1H
1G
1F
1C
0>
0<
0:
08
b10000000010001110 [
b10000000010001110 %
#460
b101110 '
b101110 *
b101110 )
b101110 4
b1110111000101111 "
b100010110110111 #
b10011001111100110 &
b101110 6
1U
0Q
1O
0N
1M
0L
0K
0J
1I
0H
1E
0C
1B
0@
0?
1>
1<
1:
18
b10011001111100110 [
b10011001111100110 %
#470
b101111 '
b101111 *
b101111 )
b101111 4
b1101000100001011 "
b11101011100111 #
b10000101111110010 &
b101111 6
0S
1Q
0O
1N
0M
1L
1K
1J
0I
0E
0B
1?
0>
0=
0<
1;
0:
b10000101111110010 [
b10000101111110010 %
#480
b110000 '
b110000 *
b110000 )
b110000 4
b1010110100000000 "
b100100100001001 #
b1111011000001001 &
b110000 6
0V
0U
1T
0R
0Q
0P
1O
0N
0K
0J
1I
0G
0F
0D
1=
1<
0;
1:
09
b1111011000001001 [
b1111011000001001 %
#490
b110001 '
b110001 *
b110001 )
b110001 4
b1010001001101010 "
b11101011000001 #
b1101110100101011 &
b110001 6
0T
1Q
1P
0O
1N
1K
1J
0I
1F
1D
1B
1A
0?
1>
0=
0<
b1101110100101011 [
b1101110100101011 %
#500
b110010 '
b110010 *
b110010 )
b110010 4
b1111000000100 "
b1010111101100000 #
b1100110101100100 &
b110010 6
0W
1R
0P
1O
1M
0K
1H
0F
1E
0D
0B
0A
1=
1<
1;
0:
08
b1100110101100100 [
b1100110101100100 %
#510
b110011 '
b110011 *
b110011 )
b110011 4
b100001110101111 "
b1100010101101111 #
b10000100100011110 &
b110011 6
1W
1V
1U
1T
0N
0L
0J
1I
1G
1F
1D
1B
1@
1?
0=
0<
0;
19
b10000100100011110 [
b10000100100011110 %
#520
b110100 '
b110100 *
b110100 )
b110100 4
b1001100101000101 "
b1110011111001101 #
b11000000100010010 &
b110100 6
0V
0R
1P
1N
1J
0F
0D
0B
1A
0@
0>
1<
1;
09
18
b11000000100010010 [
b11000000100010010 %
#530
b110101 '
b110101 *
b110101 )
b110101 4
b111011101101100 "
b11111011010000 #
b1011011000111100 &
b110101 6
0W
0U
0T
1S
0O
1L
1K
0I
0H
0G
1D
1B
1>
1=
0<
1:
19
08
b1011011000111100 [
b1011011000111100 %
#540
b110110 '
b110110 *
b110110 )
b110110 4
b100000010101001 "
b1100110111111100 #
b10000111010100101 &
b110110 6
1U
1T
1R
1O
0N
0K
0J
1I
1H
1G
0E
0A
1@
0?
0>
0=
0;
0:
b10000111010100101 [
b10000111010100101 %
#550
b110111 '
b110111 *
b110111 )
b110111 4
b1100001011100101 "
b111000010100111 #
b10011001110001100 &
b110111 6
1W
1V
0T
0S
0Q
0O
0M
0L
1K
1J
0H
1E
0D
1A
1>
18
b10011001110001100 [
b10011001110001100 %
#560
b111000 '
b111000 *
b111000 )
b111000 4
b100000000111011 "
b1101100010111110 #
b10001100011111001 &
b111000 6
0W
1T
1S
1L
0J
1H
1F
0E
1D
1C
0A
0@
0>
08
b10001100011111001 [
b10001100011111001 %
#570
b111001 '
b111001 *
b111001 )
b111001 4
b111101010100001 "
b10010110000101 #
b1010000000100110 &
b111001 6
1W
0V
0T
0S
0R
1O
1M
0L
0K
1J
0I
0H
0F
0D
0C
1@
1>
1<
1;
1:
b1010000000100110 [
b1010000000100110 %
#580
b111010 '
b111010 *
b111010 )
b111010 4
b10111110001110 "
b1101111110100000 #
b10000111100101110 &
b111010 6
0W
0U
1R
1N
1L
1K
0J
1I
1H
0G
1F
1E
1D
0B
1?
1=
0;
09
b10000111100101110 [
b10000111100101110 %
#590
b111011 '
b111011 *
b111011 )
b111011 4
b110000100010101 "
b1001000000000000 #
b1111000100010101 &
b111011 6
0R
0P
0O
0N
0M
0L
0I
1G
0F
0D
1C
0@
0>
0=
0<
19
b1111000100010101 [
b1111000100010101 %
#600
b111100 '
b111100 *
b111100 )
b111100 4
b1011100111000100 "
b1011011110001011 #
b10111000101001111 &
b111100 6
1W
1V
1T
1P
1O
1N
1M
1J
0G
0C
1A
1@
1<
1;
09
18
b10111000101001111 [
b10111000101001111 %
#610
b111101 '
b111101 *
b111101 )
b111101 4
b1011000010101000 "
b110011010111101 #
b10001011101100101 &
b111101 6
0V
1U
1S
1R
0O
0K
1I
0H
0E
1D
1B
0A
0?
0<
b10001011101100101 [
b10001011101100101 %
#620
b111110 '
b111110 *
b111110 )
b111110 4
b110101001101100 "
b1110101101111101 #
b10101010111101001 &
b111110 6
1Q
0P
1O
0M
1L
1H
1E
1A
0@
1>
1<
0;
19
08
b10101010111101001 [
b10101010111101001 %
#630
b111111 '
b111111 *
b111111 )
b111111 4
b1011010101011 "
b1101000110101010 #
b1110100001010101 &
b111111 6
0W
1V
0U
0S
0Q
1P
0N
0L
1K
0J
1G
1F
0E
0A
1@
1=
0<
1;
0:
09
b1110100001010101 [
b1110100001010101 %
#640
b1000000 '
b1000000 *
b1000000 )
b1000000 4
b101010101100001 "
b1101010110010 #
b111000000010011 &
b1000000 6
0T
1S
0O
1N
1L
0I
0H
0F
0D
1A
0@
1?
0>
19
b111000000010011 [
b111000000010011 %
#650
b1000001 '
b1000001 *
b1000001 )
b1000001 4
b101000101010110 "
b1110101001000110 #
b10011101110011100 &
b1000001 6
1U
0S
0R
1Q
0P
0K
1J
1I
1H
0G
1F
1E
1C
0B
0=
b10011101110011100 [
b10011101110011100 %
#660
b1000010 '
b1000010 *
b1000010 )
b1000010 4
b11100011010100 "
b10001011100001 #
b101101110110101 &
b1000010 6
1W
0V
0U
1R
1P
0L
0I
0H
0F
1@
0?
1<
1:
09
b101101110110101 [
b101101110110101 %
#670
b1000011 '
b1000011 *
b1000011 )
b1000011 4
b1110111111010100 "
b1111010000100001 #
b11110001111110101 &
b1000011 6
0Q
0P
0N
1M
1K
1I
1H
1?
1>
1=
0;
19
18
b11110001111110101 [
b11110001111110101 %
#680
b1000100 '
b1000100 *
b1000100 )
b1000100 4
b1111100101100000 "
b101011101101001 #
b10101000011001001 &
b1000100 6
1T
1Q
1O
1N
0J
0H
0E
0C
1B
0@
0>
0=
1;
b10101000011001001 [
b10101000011001001 %
#690
b1000101 '
b1000101 *
b1000101 )
b1000101 4
b1011011000000110 "
b111011111110100 #
b10010110111111010 &
b1000101 6
0W
1U
0T
1S
1P
1J
1F
1E
0B
0A
0?
1>
1=
0<
09
b10010110111111010 [
b10010110111111010 %
#700
b1000110 '
b1000110 *
b1000110 )
b1000110 4
b11011001111110 "
b1001010011001010 #
b1100101101001000 &
b1000110 6
1V
0U
1T
0S
0R
0O
0N
0J
0I
1H
1D
1C
1B
1A
08
b1100101101001000 [
b1100101101001000 %
#710
b1000111 '
b1000111 *
b1000111 )
b1000111 4
b111001000101000 "
b100000000011 #
b111101000101011 &
b1000111 6
1W
0T
0Q
0P
0M
1L
0K
0H
0F
0E
0C
0A
0=
19
b111101000101011 [
b111101000101011 %
#720
b1001000 '
b1001000 *
b1001000 )
b1001000 4
b110110110101111 "
b1101001111101100 #
b10100000110011011 &
b1001000 6
0W
0V
1U
1T
1R
1Q
1P
1O
1N
0L
1K
1I
1H
1G
1F
1E
1@
1?
0>
1=
1<
0;
b10100000110011011 [
b10100000110011011 %
#730
b1001001 '
b1001001 *
b1001001 )
b1001001 4
b100001101111110 "
b110010001000110 #
b1010011111000100 &
b1001001 6
1V
0T
0R
0P
0O
0N
1M
0K
1J
0H
0G
1C
1A
0@
1>
0=
0<
0:
b1010011111000100 [
b1010011111000100 %
#740
b1001010 '
b1001010 *
b1001010 )
b1001010 4
b101100101001000 "
b110011011000101 #
b1100000000001101 &
b1001010 6
1W
0V
1P
1N
0F
0E
0C
0B
0>
1<
1;
b1100000000001101 [
b1100000000001101 %
#750
b1001011 '
b1001011 *
b1001011 )
b1001011 4
b1001011111111110 "
b1110011010100100 #
b10111111010100010 &
b1001011 6
0W
1R
0Q
1H
1F
1E
1C
1B
1@
1>
1=
0<
09
18
b10111111010100010 [
b10111111010100010 %
#760
b1001100 '
b1001100 *
b1001100 )
b1001100 4
b1011110101110101 "
b1111000000001101 #
b11010110110000010 &
b1001100 6
1W
1T
0R
0P
0N
0M
1K
1G
0F
0D
0@
0>
1<
1:
b11010110110000010 [
b11010110110000010 %
#770
b1001101 '
b1001101 *
b1001101 )
b1001101 4
b1001011001110110 "
b10110001111101 #
b1100001011110011 &
b1001101 6
1S
1R
1Q
1M
1L
0K
0I
0H
0G
1F
0?
1>
0<
0:
b1100001011110011 [
b1100001011110011 %
#780
b1001110 '
b1001110 *
b1001110 )
b1001110 4
b1010110100011111 "
b1010110111111001 #
b10101101100011000 &
b1001110 6
0U
1P
1O
1H
1G
1D
0B
0A
1?
0>
1<
0;
1:
b10101101100011000 [
b10101101100011000 %
#790
b1001111 '
b1001111 *
b1001111 )
b1001111 4
b1001001001111001 "
b1100101000100001 #
b10101110010011010 &
b1001111 6
0T
0S
0Q
0P
0O
1N
0M
0J
1I
0F
0E
1B
1A
0?
1>
0=
0<
1;
0:
b10101110010011010 [
b10101110010011010 %
#800
b1010000 '
b1010000 *
b1010000 )
b1010000 4
b10100001101101 "
b1110101011011101 #
b10001001101001010 &
b1010000 6
1U
1T
1S
0R
1Q
1P
1J
1E
0C
0>
1<
0;
1:
08
b10001001101001010 [
b10001001101001010 %
#810
b1010001 '
b1010001 *
b1010001 )
b1010001 4
b10001011001111 "
b100001111110001 #
b110011011000000 &
b1010001 6
0U
0T
1R
1O
0L
0J
0H
1F
0B
1@
1>
0<
b110011011000000 [
b110011011000000 %
#820
b1010010 '
b1010010 *
b1010010 )
b1010010 4
b1100111001100101 "
b1010010110011010 #
b10111001111111111 &
b1010010 6
0W
1V
1T
0R
0Q
0N
1M
1J
0I
1H
0F
0D
1B
0@
1=
1<
0:
19
18
b10111001111111111 [
b10111001111111111 %
#830
b1010011 '
b1010011 *
b1010011 )
b1010011 4
b101111101110000 "
b101101110101000 #
b1011101100011000 &
b1010011 6
0V
0S
1R
1N
0M
1L
1K
0J
1I
0H
0G
0E
1C
1?
1;
08
b1011101100011000 [
b1011101100011000 %
#840
b1010100 '
b1010100 *
b1010100 )
b1010100 4
b1001011101110110 "
b10001111101110 #
b1011101101100100 &
b1010100 6
1V
1U
1Q
0L
0K
1J
0I
1F
1E
0<
09
18
b1011101101100100 [
b1011101101100100 %
#850
b1010101 '
b1010101 *
b1010101 )
b1010101 4
b1011100110110100 "
b101000100011000 #
b10000101011001100 &
b1010101 6
0V
0U
1S
0R
0Q
0P
0N
1K
0J
1I
0F
0A
1@
0>
0=
1<
1:
b10000101011001100 [
b10000101011001100 %
#860
b1010110 '
b1010110 *
b1010110 )
b1010110 4
b1001101001010001 "
b1110001001111100 #
b10111110011001101 &
b1010110 6
1U
1R
1Q
0O
1N
0K
1J
1H
1G
0E
0B
1A
0@
0?
1>
0:
b10111110011001101 [
b10111110011001101 %
#870
b1010111 '
b1010111 *
b1010111 )
b1010111 4
b111001101001101 "
b10010011000001 #
b1001100000001110 &
b1010111 6
1W
0U
0T
0S
0R
1P
0N
1M
0I
0H
1E
1D
0C
1?
0<
1:
19
08
b1001100000001110 [
b1001100000001110 %
#880
b1011000 '
b1011000 *
b1011000 )
b1011000 4
b110111010110111 "
b101001000110 #
b111100011111101 &
b1011000 6
0W
1V
1U
0P
1N
0M
1L
0J
1F
0D
1C
1B
0A
1@
0?
1=
1<
0;
b111100011111101 [
b111100011111101 %
#890
b1011001 '
b1011001 *
b1011001 )
b1011001 4
b1010011011110000 "
b111100100100111 #
b10010000000010111 &
b1011001 6
1W
1R
0Q
1O
0N
1K
1J
1I
0G
0F
0E
1A
0<
09
18
b10010000000010111 [
b10010000000010111 %
#900
b1011010 '
b1011010 *
b1011010 )
b1011010 4
b110000101110011 "
b10011100111100 #
b1000100010101111 &
b1011010 6
0W
0V
1T
1S
1N
1M
0L
0K
0I
1G
1F
0@
1?
0>
0=
19
08
b1000100010101111 [
b1000100010101111 %
